[{"type":"Feature","geometry":{"type":"Point","coordinates":[-118.190979,34.11917]},"properties":{"listingKey":"20251101174441507219000000","listingId":"GD-25251502","listPrice":1100000,"city":"Los Angeles","baths":1.75,"slug":"20251101174441507219000000","mlsSource":"CRMLS","propertyType":"A","propertySubType":"Single Family Residence","livingArea":1488,"associationFee":0,"unparsedAddress":"5830 Fayette, Los Angeles, CA 90042"}},{"type":"Feature","geometry":{"type":"Point","coordinates":[-118.191266,34.120669]},"properties":{"listingKey":"20250719062250024891000000","listingId":"OC-25161732","listPrice":850000,"city":"Los Angeles","baths":1,"slug":"20250719062250024891000000","mlsSource":"CRMLS","propertyType":"A","propertySubType":"Single Family Residence","livingArea":820,"associationFee":0,"unparsedAddress":"5807 Meridian Street, Los Angeles, CA 90042"}},{"type":"Feature","geometry":{"type":"Point","coordinates":[-118.201773,34.116564]},"properties":{"listingKey":"20250717001122314871000000","listingId":"DW-25159858","listPrice":1350000,"city":"Los Angeles","baths":2,"slug":"20250717001122314871000000","mlsSource":"CRMLS","propertyType":"A","propertySubType":"Single Family Residence","livingArea":1272,"associationFee":0,"unparsedAddress":"829 North Avenue 53, Los Angeles, CA 90042"}},{"type":"Feature","geometry":{"type":"Point","coordinates":[-118.198569,34.117824]},"properties":{"listingKey":"20250909193601100833000000","listingId":"IV-25155178","listPrice":1975,"city":"Los Angeles","baths":0.75,"slug":"20250909193601100833000000","mlsSource":"CRMLS","propertyType":"B","propertySubType":"Triplex","livingArea":506,"associationFee":0,"unparsedAddress":"5417 Baltimore Street, Los Angeles, CA 90042"}},{"type":"Feature","geometry":{"type":"Point","coordinates":[-118.197369,34.124837]},"properties":{"listingKey":"20251016202006905983000000","listingId":"CV-25241156","listPrice":849900,"city":"Los Angeles","baths":1,"slug":"20251016202006905983000000","mlsSource":"CRMLS","propertyType":"A","propertySubType":"Single Family Residence","livingArea":736,"associationFee":0,"unparsedAddress":"1800 North Avenue 55, Los Angeles, CA 90042"}}]