[{"type":"Feature","geometry":{"type":"Point","coordinates":[-116.273815,32.663625]},"properties":{"listingKey":"20251003000518487087000000","listingId":"8N-2509543","listPrice":500000,"city":"San Diego","baths":1,"slug":"20251003000518487087000000","mlsSource":"CRMLS","propertyType":"A","propertySubType":"Condominium","livingArea":738,"associationFee":400,"unparsedAddress":"550 Park Boulevard, 2306, San Diego, CA 92101"}},{"type":"Feature","id":101508,"properties":{"cluster":true,"cluster_id":101508,"point_count":4,"point_count_abbreviated":4},"geometry":{"type":"Point","coordinates":[-116.32454305887222,32.66025581912389]}}]