[{"type":"Feature","id":138214,"properties":{"cluster":true,"cluster_id":138214,"point_count":6,"point_count_abbreviated":6},"geometry":{"type":"Point","coordinates":[-117.98298418521883,33.650227375911356]}},{"type":"Feature","geometry":{"type":"Point","coordinates":[-117.968553,33.641241]},"properties":{"listingKey":"20251024200800499005000000","listingId":"OC-25246575","listPrice":5250000,"city":"Huntington Beach","baths":4.5,"slug":"20251024200800499005000000","mlsSource":"CRMLS","propertyType":"A","propertySubType":"Single Family Residence","livingArea":4912,"associationFee":0,"unparsedAddress":"9121 Christine Drive, Huntington Beach, CA 92646"}},{"type":"Feature","id":64838,"properties":{"cluster":true,"cluster_id":64838,"point_count":13,"point_count_abbreviated":13},"geometry":{"type":"Point","coordinates":[-117.95115159108089,33.62823066817194]}}]