[{"type":"Feature","geometry":{"type":"Point","coordinates":[-117.591768,33.561573]},"properties":{"listingKey":"20250610050144374694000000","listingId":"OC-25129523","listPrice":3450000,"city":"Coto de Caza","baths":4.5,"slug":"20250610050144374694000000","mlsSource":"CRMLS","propertyType":"A","propertySubType":"Single Family Residence","livingArea":5070,"associationFee":270,"unparsedAddress":"18 Bent Oak, Coto de Caza, CA 92679"}},{"type":"Feature","geometry":{"type":"Point","coordinates":[-117.592792,33.565647]},"properties":{"listingKey":"20250914205844492374000000","listingId":"OC-25217051","listPrice":10250,"city":"Coto de Caza","baths":5.5,"slug":"20250914205844492374000000","mlsSource":"CRMLS","propertyType":"B","propertySubType":"Single Family Residence","livingArea":5070,"associationFee":225,"unparsedAddress":"12 Lone Wolf, Coto de Caza, CA 92679"}},{"type":"Feature","geometry":{"type":"Point","coordinates":[-117.588837,33.571216]},"properties":{"listingKey":"20251107095450826064000000","listingId":"OC-25255936","listPrice":2349000,"city":"Coto de Caza","baths":3.75,"slug":"20251107095450826064000000","mlsSource":"CRMLS","propertyType":"A","propertySubType":"Single Family Residence","livingArea":3541,"associationFee":353,"unparsedAddress":"2 AQUILA Way, Coto de Caza, CA 92679"}},{"type":"Feature","geometry":{"type":"Point","coordinates":[-117.580885,33.572299]},"properties":{"listingKey":"20250806214644707569000000","listingId":"OC-25175284","listPrice":3070000,"city":"Coto de Caza","baths":4.5,"slug":"20250806214644707569000000","mlsSource":"CRMLS","propertyType":"A","propertySubType":"Single Family Residence","livingArea":4232,"associationFee":353,"unparsedAddress":"3 Hubbard Way, Coto de Caza, CA 92679"}},{"type":"Feature","id":338057,"properties":{"cluster":true,"cluster_id":338057,"point_count":2,"point_count_abbreviated":2},"geometry":{"type":"Point","coordinates":[-117.58950769901276,33.56316653271995]}},{"type":"Feature","id":847208,"properties":{"cluster":true,"cluster_id":847208,"point_count":3,"point_count_abbreviated":3},"geometry":{"type":"Point","coordinates":[-117.58309364318849,33.56527934824834]}},{"type":"Feature","geometry":{"type":"Point","coordinates":[-117.590411,33.575779]},"properties":{"listingKey":"20250621153415709683000000","listingId":"OC-25133780","listPrice":5788000,"city":"Coto de Caza","baths":5,"slug":"20250621153415709683000000","mlsSource":"CRMLS","propertyType":"A","propertySubType":"Single Family Residence","livingArea":4490,"associationFee":353,"unparsedAddress":"106 Panorama, Coto de Caza, CA 92679"}},{"type":"Feature","id":278088,"properties":{"cluster":true,"cluster_id":278088,"point_count":2,"point_count_abbreviated":2},"geometry":{"type":"Point","coordinates":[-117.58863598108292,33.57296431594905]}}]