[{"type":"Feature","id":223145,"properties":{"cluster":true,"cluster_id":223145,"point_count":2,"point_count_abbreviated":2},"geometry":{"type":"Point","coordinates":[-117.7397945523262,33.57042558103403]}},{"type":"Feature","id":760169,"properties":{"cluster":true,"cluster_id":760169,"point_count":2,"point_count_abbreviated":2},"geometry":{"type":"Point","coordinates":[-117.73594826459885,33.57459121245158]}},{"type":"Feature","geometry":{"type":"Point","coordinates":[-117.736664,33.573435]},"properties":{"listingKey":"20251120225801442183000000","listingId":"OC-25260855","listPrice":3100,"city":"Aliso Viejo","baths":2,"slug":"20251120225801442183000000","mlsSource":"CRMLS","propertyType":"B","propertySubType":"Condominium","livingArea":962,"unparsedAddress":"64 Bryce Canyon, Aliso Viejo, CA 92656"}},{"type":"Feature","id":280041,"properties":{"cluster":true,"cluster_id":280041,"point_count":2,"point_count_abbreviated":2},"geometry":{"type":"Point","coordinates":[-117.73214757442474,33.57250842186893]}},{"type":"Feature","geometry":{"type":"Point","coordinates":[-117.732828,33.5765]},"properties":{"listingKey":"20251111234335760024000000","listingId":"OC-25258014","listPrice":1488888,"city":"Aliso Viejo","baths":2.5,"slug":"20251111234335760024000000","mlsSource":"CRMLS","propertyType":"A","propertySubType":"Single Family Residence","livingArea":1900,"associationFee":234,"unparsedAddress":"6 Plateau, Aliso Viejo, CA 92656"}},{"type":"Feature","geometry":{"type":"Point","coordinates":[-117.734741,33.577645]},"properties":{"listingKey":"20251024234343276387000000","listingId":"OC-25247041","listPrice":4000,"city":"Aliso Viejo","baths":2.5,"slug":"20251024234343276387000000","mlsSource":"CRMLS","propertyType":"B","propertySubType":"Single Family Residence","livingArea":1334,"unparsedAddress":"4 Maison, Aliso Viejo, CA 92656"}}]