[{"type":"Feature","geometry":{"type":"Point","coordinates":[-119.005353,34.21896]},"properties":{"listingKey":"20250914102752898016000000","listingId":"V1-32334","listPrice":700000,"city":"Camarillo","baths":2,"slug":"20250914102752898016000000","mlsSource":"CRMLS","propertyType":"A","propertySubType":"Single Family Residence","livingArea":1151,"associationFee":292,"unparsedAddress":"369 Estancia Place, Camarillo, CA 93012"}},{"type":"Feature","id":512905,"properties":{"cluster":true,"cluster_id":512905,"point_count":2,"point_count_abbreviated":2},"geometry":{"type":"Point","coordinates":[-119.01194214820862,34.22353504941971]}},{"type":"Feature","geometry":{"type":"Point","coordinates":[-119.012628,34.218763]},"properties":{"listingKey":"20250825220809863634000000","listingId":"V1-32095","listPrice":739999,"city":"Camarillo","baths":2.5,"slug":"20250825220809863634000000","mlsSource":"CRMLS","propertyType":"A","propertySubType":"Townhouse","livingArea":1537,"associationFee":500,"unparsedAddress":"269 Via Cantilena, Camarillo, CA 93012"}},{"type":"Feature","geometry":{"type":"Point","coordinates":[-119.021398,34.230341]},"properties":{"listingKey":"20251104165636342445000000","listingId":"V1-33210","listPrice":879000,"city":"Camarillo","baths":2,"slug":"20251104165636342445000000","mlsSource":"CRMLS","propertyType":"A","propertySubType":"Single Family Residence","livingArea":1754,"unparsedAddress":"3623 Corona Street, Camarillo, CA 93010"}},{"type":"Feature","geometry":{"type":"Point","coordinates":[-119.015747,34.231358]},"properties":{"listingKey":"20251026215736139408000000","listingId":"V1-33074","listPrice":639900,"city":"Camarillo","baths":3,"slug":"20251026215736139408000000","mlsSource":"CRMLS","propertyType":"A","propertySubType":"Condominium","livingArea":1324,"associationFee":374,"unparsedAddress":"4514 Via Presidio, Camarillo, CA 93012"}}]