[{"type":"Feature","geometry":{"type":"Point","coordinates":[-122.40315,40.699823]},"properties":{"listingKey":"20250823063256790551000000","listingId":"FR-25189903","listPrice":534900,"city":"Shasta Lake","baths":2,"slug":"20250823063256790551000000","mlsSource":"CRMLS","propertyType":"A","propertySubType":"Single Family Residence","livingArea":2028,"associationFee":0,"unparsedAddress":"14153 Lake Boulevard, Shasta Lake, CA 96019"}},{"type":"Feature","id":68163,"properties":{"cluster":true,"cluster_id":68163,"point_count":2,"point_count_abbreviated":2},"geometry":{"type":"Point","coordinates":[-122.39129483699799,40.571306995890154]}},{"type":"Feature","geometry":{"type":"Point","coordinates":[-122.948788,40.644322]},"properties":{"listingKey":"20250916202437917035000000","listingId":"01-41111705","listPrice":625000,"city":"Douglas City","baths":2.5,"slug":"20250916202437917035000000","mlsSource":"CRMLS","propertyType":"A","propertySubType":"Manufactured On Land","livingArea":1280,"unparsedAddress":"30661 State Hwy 3, Douglas City, CA 96024"}},{"type":"Feature","id":130085,"properties":{"cluster":true,"cluster_id":130085,"point_count":6,"point_count_abbreviated":6},"geometry":{"type":"Point","coordinates":[-122.93650388717653,40.73213422038921]}},{"type":"Feature","geometry":{"type":"Point","coordinates":[-122.396956,40.858205]},"properties":{"listingKey":"20250913071704947807000000","listingId":"IG-25216543","listPrice":370000,"baths":2,"slug":"20250913071704947807000000","mlsSource":"CRMLS","propertyType":"A","propertySubType":"Single Family Residence","livingArea":1008,"associationFee":0,"unparsedAddress":"753 Maple, CA 92333"}},{"type":"Feature","id":57667,"properties":{"cluster":true,"cluster_id":57667,"point_count":4,"point_count_abbreviated":4},"geometry":{"type":"Point","coordinates":[-122.83779010176659,40.715626971313014]}},{"type":"Feature","geometry":{"type":"Point","coordinates":[-122.783349,40.910889]},"properties":{"listingKey":"20251014220630911299000000","listingId":"01-41114692","listPrice":213000,"city":"Trinity Center","baths":1,"slug":"20251014220630911299000000","mlsSource":"CRMLS","propertyType":"A","propertySubType":"Single Family Residence","livingArea":980,"unparsedAddress":"761 Lake Forest Dr., Trinity Center, CA 96091"}}]