[{"type":"Feature","geometry":{"type":"Point","coordinates":[-122.045601,37.71685]},"properties":{"listingKey":"20251007011540602184000000","listingId":"01-41113924","listPrice":2100000,"city":"Castro Valley","baths":2.5,"slug":"20251007011540602184000000","mlsSource":"CRMLS","propertyType":"A","propertySubType":"Single Family Residence","livingArea":3119,"unparsedAddress":"6066 Monte Verde Ct, Castro Valley, CA 94552"}},{"type":"Feature","geometry":{"type":"Point","coordinates":[-122.048598,37.716238]},"properties":{"listingKey":"20251007012304580807000000","listingId":"01-41113910","listPrice":1498000,"city":"Castro Valley","baths":2,"slug":"20251007012304580807000000","mlsSource":"CRMLS","propertyType":"A","propertySubType":"Single Family Residence","livingArea":1908,"associationFee":260,"unparsedAddress":"5513 Rothman Ct, Castro Valley, CA 94552"}}]