[{"type":"Feature","geometry":{"type":"Point","coordinates":[-117.641938,33.8795]},"properties":{"listingKey":"20250814081212801793000000","listingId":"PW-25183267","listPrice":1249998,"city":"Corona","baths":2.5,"slug":"20250814081212801793000000","mlsSource":"CRMLS","propertyType":"A","propertySubType":"Single Family Residence","livingArea":3274,"associationFee":220,"unparsedAddress":"965 Manor Way, Corona, CA 92882"}},{"type":"Feature","geometry":{"type":"Point","coordinates":[-117.644739,33.871868]},"properties":{"listingKey":"20251110211033342364000000","listingId":"IG-25256768","listPrice":1032500,"city":"Corona","baths":3,"slug":"20251110211033342364000000","mlsSource":"CRMLS","propertyType":"A","propertySubType":"Single Family Residence","livingArea":2655,"associationFee":52,"unparsedAddress":"1611 San Almada, Corona, CA 92882"}}]