[{"type":"Feature","geometry":{"type":"Point","coordinates":[-122.211315,39.51546]},"properties":{"listingKey":"20250729060814837179000000","listingId":"SN-25169908","listPrice":359000,"city":"Willows","baths":2,"slug":"20250729060814837179000000","mlsSource":"CRMLS","propertyType":"A","propertySubType":"Single Family Residence","livingArea":1299,"associationFee":0,"unparsedAddress":"461 El Dorado Avenue, Willows, CA 95988"}},{"type":"Feature","id":304328,"properties":{"cluster":true,"cluster_id":304328,"point_count":2,"point_count_abbreviated":2},"geometry":{"type":"Point","coordinates":[-122.20117717981339,39.515376710500476]}},{"type":"Feature","geometry":{"type":"Point","coordinates":[-122.205543,39.512959]},"properties":{"listingKey":"20251118203456768212000000","listingId":"SN-25259774","listPrice":284000,"city":"Willows","baths":1,"slug":"20251118203456768212000000","mlsSource":"CRMLS","propertyType":"A","propertySubType":"Single Family Residence","livingArea":1063,"associationFee":0,"unparsedAddress":"939 Elm Street, Willows, CA 95988"}},{"type":"Feature","id":430729,"properties":{"cluster":true,"cluster_id":430729,"point_count":2,"point_count_abbreviated":2},"geometry":{"type":"Point","coordinates":[-122.19773590564728,39.51769831462917]}},{"type":"Feature","geometry":{"type":"Point","coordinates":[-122.197047,39.514846]},"properties":{"listingKey":"20250827132540305218000000","listingId":"SN-25192530","listPrice":285000,"city":"Willows","baths":2,"slug":"20250827132540305218000000","mlsSource":"CRMLS","propertyType":"A","propertySubType":"Single Family Residence","livingArea":1454,"associationFee":0,"unparsedAddress":"529 South Shasta Street, Willows, CA 95988"}},{"type":"Feature","geometry":{"type":"Point","coordinates":[-122.193587,39.510344]},"properties":{"listingKey":"20250812073008549138000000","listingId":"SN-25181036","listPrice":172000,"city":"Willows","baths":1,"slug":"20250812073008549138000000","mlsSource":"CRMLS","propertyType":"A","propertySubType":"Single Family Residence","livingArea":932,"associationFee":0,"unparsedAddress":"818 South Tehama Street, Willows, CA 95988"}},{"type":"Feature","geometry":{"type":"Point","coordinates":[-122.190397,39.518247]},"properties":{"listingKey":"20251118191853729110000000","listingId":"01-41117636","listPrice":1499000,"city":"Willows","baths":0,"slug":"20251118191853729110000000","mlsSource":"CRMLS","propertyType":"C","associationFee":0,"unparsedAddress":"266 South Yolo St, Willows, CA 95988"}}]