[{"type":"Feature","geometry":{"type":"Point","coordinates":[-122.373231,37.727801]},"properties":{"listingKey":"20250716194231718785000000","listingId":"01-41104926","listPrice":650000,"city":"San Francisco","baths":3,"slug":"20250716194231718785000000","mlsSource":"CRMLS","propertyType":"A","propertySubType":"Condominium","livingArea":1360,"associationFee":726,"unparsedAddress":"137 Nautilus Ct, 82, San Francisco, CA 94124"}},{"type":"Feature","geometry":{"type":"Point","coordinates":[-122.369113,37.728519]},"properties":{"listingKey":"20251008020904903183000000","listingId":"01-41114057","listPrice":175000,"city":"San Francisco","baths":1,"slug":"20251008020904903183000000","mlsSource":"CRMLS","propertyType":"A","propertySubType":"Condominium","livingArea":764,"associationFee":566,"unparsedAddress":"570 Innes Ave, 201, San Francisco, CA 94124"}}]