[{"type":"Feature","id":142823,"properties":{"cluster":true,"cluster_id":142823,"point_count":7,"point_count_abbreviated":7},"geometry":{"type":"Point","coordinates":[-116.96560595716748,33.69023541947496]}},{"type":"Feature","geometry":{"type":"Point","coordinates":[-116.943533,33.690444]},"properties":{"listingKey":"20251016061421190227000000","listingId":"IV-25240788","listPrice":639900,"city":"Hemet","baths":2,"slug":"20251016061421190227000000","mlsSource":"CRMLS","propertyType":"A","propertySubType":"Single Family Residence","livingArea":2187,"associationFee":0,"unparsedAddress":"42557 Gibbel Rd, Hemet, CA 92544"}},{"type":"Feature","id":321831,"properties":{"cluster":true,"cluster_id":321831,"point_count":3,"point_count_abbreviated":3},"geometry":{"type":"Point","coordinates":[-116.98227524757384,33.72423258124353]}},{"type":"Feature","id":356167,"properties":{"cluster":true,"cluster_id":356167,"point_count":9,"point_count_abbreviated":9},"geometry":{"type":"Point","coordinates":[-116.97025179862977,33.69236821691382]}}]