[{"type":"Feature","geometry":{"type":"Point","coordinates":[-120.915401,40.098316]},"properties":{"listingKey":"20250918042942465995000000","listingId":"01-41111882","listPrice":269000,"city":"Crescent Mills","baths":2,"slug":"20250918042942465995000000","mlsSource":"CRMLS","propertyType":"A","propertySubType":"Single Family Residence","livingArea":1440,"unparsedAddress":"286 Carter Steet, Crescent Mills, CA 95934"}},{"type":"Feature","geometry":{"type":"Point","coordinates":[-120.865225,39.939059]},"properties":{"listingKey":"20251114003127700377000000","listingId":"SN-25260186","listPrice":429000,"city":"Quincy","baths":2,"slug":"20251114003127700377000000","mlsSource":"CRMLS","propertyType":"A","propertySubType":"Single Family Residence","livingArea":1722,"associationFee":0,"unparsedAddress":"226 Chandler, Quincy, CA 95971"}}]