[{"type":"Feature","geometry":{"type":"Point","coordinates":[-116.315892,33.734592]},"properties":{"listingKey":"20251014224945717483000000","listingId":"219136955","listPrice":475000,"city":"Palm Desert","baths":2,"slug":"20251014224945717483000000","mlsSource":"GPS","propertyType":"A","propertySubType":"Single Family Residence","livingArea":1400,"associationFee":32,"unparsedAddress":"43305 Illinois Avenue, Palm Desert, CA 92211"}},{"type":"Feature","geometry":{"type":"Point","coordinates":[-116.320782,33.734497]},"properties":{"listingKey":"20251028191603282954000000","listingId":"219137812","listPrice":550000,"city":"Palm Desert","baths":2,"slug":"20251028191603282954000000","mlsSource":"GPS","propertyType":"A","propertySubType":"Single Family Residence","livingArea":1755,"associationFee":195,"unparsedAddress":"77310 Colorado Street, Palm Desert, CA 92211"}},{"type":"Feature","geometry":{"type":"Point","coordinates":[-116.31988,33.735499]},"properties":{"listingKey":"20251027005005225956000000","listingId":"219137661","listPrice":574890,"city":"Palm Desert","baths":2.5,"slug":"20251027005005225956000000","mlsSource":"GPS","propertyType":"A","propertySubType":"Single Family Residence","livingArea":1755,"associationFee":165,"unparsedAddress":"77405 Colorado St Street, Palm Desert, CA 92211"}},{"type":"Feature","id":44489,"properties":{"cluster":true,"cluster_id":44489,"point_count":4,"point_count_abbreviated":4},"geometry":{"type":"Point","coordinates":[-116.32259979844093,33.73963741563341]}},{"type":"Feature","geometry":{"type":"Point","coordinates":[-116.318556,33.739781]},"properties":{"listingKey":"20251030161903483182000000","listingId":"IG-25250319","listPrice":405000,"city":"Palm Desert","baths":2,"slug":"20251030161903483182000000","mlsSource":"CRMLS","propertyType":"A","propertySubType":"Single Family Residence","livingArea":1064,"associationFee":33,"unparsedAddress":"42585 Iowa Street, Palm Desert, CA 92211"}},{"type":"Feature","id":79401,"properties":{"cluster":true,"cluster_id":79401,"point_count":2,"point_count_abbreviated":2},"geometry":{"type":"Point","coordinates":[-116.31677001714706,33.73892813126599]}},{"type":"Feature","geometry":{"type":"Point","coordinates":[-116.320654,33.738859]},"properties":{"listingKey":"20250919010555055564000000","listingId":"219135584","listPrice":569000,"city":"Palm Desert","baths":2.5,"slug":"20250919010555055564000000","mlsSource":"GPS","propertyType":"A","propertySubType":"Single Family Residence","livingArea":1536,"associationFee":33,"unparsedAddress":"42700 Wisconsin Avenue, Palm Desert, CA 92211"}},{"type":"Feature","geometry":{"type":"Point","coordinates":[-116.320118,33.737534]},"properties":{"listingKey":"20251108005145290223000000","listingId":"PW-25256474","listPrice":499000,"city":"Palm Desert","baths":2,"slug":"20251108005145290223000000","mlsSource":"CRMLS","propertyType":"A","propertySubType":"Single Family Residence","livingArea":1690,"associationFee":398,"unparsedAddress":"42915 Wisconsin Avenue, Palm Desert, CA 92211"}},{"type":"Feature","id":85545,"properties":{"cluster":true,"cluster_id":85545,"point_count":3,"point_count_abbreviated":3},"geometry":{"type":"Point","coordinates":[-116.3176041841507,33.74176225969529]}},{"type":"Feature","geometry":{"type":"Point","coordinates":[-116.32163,33.74081]},"properties":{"listingKey":"20250909180852833984000000","listingId":"219136425","listPrice":470000,"city":"Palm Desert","baths":1.75,"slug":"20250909180852833984000000","mlsSource":"GPS","propertyType":"A","propertySubType":"Condominium","livingArea":1384,"associationFee":998,"unparsedAddress":"42405 Turqueries Avenue, Palm Desert, CA 92211"}},{"type":"Feature","geometry":{"type":"Point","coordinates":[-116.323241,33.74188]},"properties":{"listingKey":"20250812175634891712000000","listingId":"219133966","listPrice":519000,"city":"Palm Desert","baths":2,"slug":"20250812175634891712000000","mlsSource":"GPS","propertyType":"A","propertySubType":"Condominium","livingArea":1585,"associationFee":933,"unparsedAddress":"76895 Morocco Road, Palm Desert, CA 92211"}},{"type":"Feature","id":85385,"properties":{"cluster":true,"cluster_id":85385,"point_count":2,"point_count_abbreviated":2},"geometry":{"type":"Point","coordinates":[-116.3207021355629,33.74234067209258]}},{"type":"Feature","geometry":{"type":"Point","coordinates":[-116.314089,33.741959]},"properties":{"listingKey":"20250917034529342315000000","listingId":"219135459","listPrice":385000,"city":"Palm Desert","baths":2,"slug":"20250917034529342315000000","mlsSource":"GPS","propertyType":"A","propertySubType":"Single Family Residence","livingArea":1064,"associationFee":33,"unparsedAddress":"77380 Minnesota Avenue, Palm Desert, CA 92211"}},{"type":"Feature","geometry":{"type":"Point","coordinates":[-116.314023,33.735629]},"properties":{"listingKey":"20251031210854734014000000","listingId":"219137973","listPrice":469000,"city":"Palm Desert","baths":3,"slug":"20251031210854734014000000","mlsSource":"GPS","propertyType":"A","propertySubType":"Single Family Residence","livingArea":1400,"associationFee":36,"unparsedAddress":"43120 Texas Avenue, Palm Desert, CA 92211"}},{"type":"Feature","geometry":{"type":"Point","coordinates":[-116.312286,33.735629]},"properties":{"listingKey":"20251003182848414387000000","listingId":"219136430","listPrice":1575000,"city":"Palm Desert","baths":3.25,"slug":"20251003182848414387000000","mlsSource":"GPS","propertyType":"A","propertySubType":"Single Family Residence","livingArea":3121,"associationFee":0,"unparsedAddress":"43170 Warner Trail, Palm Desert, CA 92211"}}]