[{"type":"Feature","geometry":{"type":"Point","coordinates":[-116.448164,33.921162]},"properties":{"listingKey":"20251018053243277560000000","listingId":"219137221","listPrice":170000,"city":"Desert Hot Springs","baths":0,"slug":"20251018053243277560000000","mlsSource":"GPS","propertyType":"D","associationFee":0,"unparsedAddress":"0 18th Avenue, Desert Hot Springs, CA 92241"}},{"type":"Feature","geometry":{"type":"Point","coordinates":[-116.446839,33.921095]},"properties":{"listingKey":"20251018054110197659000000","listingId":"219137223","listPrice":100000,"city":"Desert Hot Springs","baths":0,"slug":"20251018054110197659000000","mlsSource":"GPS","propertyType":"D","associationFee":0,"unparsedAddress":"0 18th Avenue, Desert Hot Springs, CA 92241"}}]