[{"type":"Feature","geometry":{"type":"Point","coordinates":[-117.446373,34.597689]},"properties":{"listingKey":"20251027221119033971000000","listingId":"CV-25248257","listPrice":280000,"city":"Adelanto","baths":2,"slug":"20251027221119033971000000","mlsSource":"CRMLS","propertyType":"A","propertySubType":"Manufactured On Land","livingArea":1248,"associationFee":0,"unparsedAddress":"19017 Panther, Adelanto, CA 92301"}},{"type":"Feature","geometry":{"type":"Point","coordinates":[-117.446409,34.598962]},"properties":{"listingKey":"20251015202848594822000000","listingId":"219137019","listPrice":35000,"city":"Adelanto","baths":0,"slug":"20251015202848594822000000","mlsSource":"GPS","propertyType":"D","associationFee":0,"unparsedAddress":"19031 Panther Ave, Adelanto, CA 92301"}}]