[{"type":"Feature","id":140457,"properties":{"cluster":true,"cluster_id":140457,"point_count":3,"point_count_abbreviated":3},"geometry":{"type":"Point","coordinates":[-117.2194755077362,34.12795209724899]}},{"type":"Feature","geometry":{"type":"Point","coordinates":[-117.214983,34.134538]},"properties":{"listingKey":"20251103030901177142000000","listingId":"IG-25251703","listPrice":420000,"city":"Highland","baths":1,"slug":"20251103030901177142000000","mlsSource":"CRMLS","propertyType":"A","propertySubType":"Single Family Residence","livingArea":1020,"associationFee":0,"unparsedAddress":"2137 Pepper Drive, Highland, CA 92346"}}]