[{"type":"Feature","geometry":{"type":"Point","coordinates":[-117.792996,33.790848]},"properties":{"listingKey":"20251025005647195696000000","listingId":"OC-25246993","listPrice":2950,"city":"Orange","baths":2,"slug":"20251025005647195696000000","mlsSource":"CRMLS","propertyType":"B","propertySubType":"Condominium","livingArea":814,"unparsedAddress":"5722 East Stillwater, 79, Orange, CA 92869"}},{"type":"Feature","geometry":{"type":"Point","coordinates":[-117.788474,33.79071]},"properties":{"listingKey":"20251104161107651975000000","listingId":"OC-25252931","listPrice":638000,"city":"Orange","baths":2.5,"slug":"20251104161107651975000000","mlsSource":"CRMLS","propertyType":"A","propertySubType":"Townhouse","livingArea":984,"associationFee":305,"unparsedAddress":"285 North Singingwood, Orange, CA 92869"}},{"type":"Feature","geometry":{"type":"Point","coordinates":[-117.790312,33.788766]},"properties":{"listingKey":"20251014231155934046000000","listingId":"OC-25239283","listPrice":725000,"city":"Orange","baths":2.5,"slug":"20251014231155934046000000","mlsSource":"CRMLS","propertyType":"A","propertySubType":"Condominium","livingArea":1190,"associationFee":352,"unparsedAddress":"177 North Singingwood Street, 22, Orange, CA 92869"}}]